.envrc
.gitignore
README.md
iskra.py
setup.py
iskra_cli.egg-info/PKG-INFO
iskra_cli.egg-info/SOURCES.txt
iskra_cli.egg-info/dependency_links.txt
iskra_cli.egg-info/requires.txt
iskra_cli.egg-info/top_level.txt
scripts/iskra